grammar_rebuild.py
usfm_grammar-3.0.0b7.dist-info/WHEEL
usfm_grammar-3.0.0b7.dist-info/top_level.txt
usfm_grammar-3.0.0b7.dist-info/entry_points.txt
usfm_grammar-3.0.0b7.dist-info/RECORD
usfm_grammar-3.0.0b7.dist-info/METADATA
usfm_grammar-3.0.0b7.dist-info/LICENSE
usfm_grammar/__init__.py
usfm_grammar/usx_generator.py
usfm_grammar/filters.py
usfm_grammar/usfm_parser.py
usfm_grammar/usj_generator.py
usfm_grammar/list_generator.py
usfm_grammar/usfm_generator.py
usfm_grammar/my-languages.so
usfm_grammar/__main__.py
