Metadata-Version: 2.1
Name: usfm-grammar
Version: 3.0.0b7
Summary: Python parser for USFM files, based on tree-sitter-usfm3
Author-email: BCS Team <joel@bridgeconn.com>
Maintainer-email: Kavitha Raju <kavitha.raju@bridgeconn.com>, Joel Mathew <joel@bridgeconn.com>
License: MIT License
Project-URL: Homepage, https://github.com/Bridgeconn/usfm-grammar/py-usfm-grammar#readme
Keywords: usfm,parser,grammar,tree-sitter
Classifier: License :: OSI Approved :: MIT License
Classifier: Programming Language :: Python :: 3
Classifier: Topic :: Software Development :: Compilers
Classifier: Topic :: Text Processing :: Markup
Classifier: Intended Audience :: Developers
Classifier: Intended Audience :: Religion
Requires-Python: >=3.10
License-File: LICENSE
Requires-Dist: tree-sitter ==0.21.3 ; python_version >= "3.3"
Requires-Dist: lxml ==5.2.2 ; python_version >= "3.5"
Provides-Extra: dev
Requires-Dist: rnc2rng ; extra == 'dev'
Requires-Dist: jupyterlab ; extra == 'dev'
Requires-Dist: pytest ; extra == 'dev'
